{
  "project_info": {
    "project_number": "571501237987",
    "project_id": "ride-lanka-bc197",
    "storage_bucket": "ride-lanka-bc197.firebasestorage.app"
  },
  "client": [
    {
      "client_info": {
        "mobilesdk_app_id": "1:571501237987:android:a5b639df339c44aadc17d6",
        "android_client_info": {
          "package_name": "com.example.ride_lanka"
        }
      },
      "oauth_client": [],
      "api_key": [
        {
          "current_key": "AIzaSyDf0l1ooJhuvjnYdMYUcJ8D1IgeDlNZrKA"
        }
      ],
      "services": {
        "appinvite_service": {
          "other_platform_oauth_client": []
        }
      }
    }
  ],
  "configuration_version": "1"
}